{"base":"pages/","current":2,"prev":1,"next":3,"current_url":"pages//2","prev_link":"pages/","next_link":"pages//3","posts":[{"title":"webpack入门篇：webpack命令行参数详解","slug":"webpack入门篇：webpack命令行参数详解","updated":1487580854468,"link":"","permalink":"http://www.fedjs.com/2017/02/webpack入门篇：webpack命令行参数详解/","path":"2017/02/webpack入门篇：webpack命令行参数详解/","photos":[],"comments":true,"source":"_posts/webpack入门篇：webpack命令行参数详解.md","published":true,"excerpt":"","content":"<h1 id=\"webpack命令行参数\"><a href=\"#webpack命令行参数\" class=\"headerlink\" title=\"webpack命令行参数\"></a>webpack命令行参数</h1><figure class=\"highlight plain\"><table><tr><td class=\"gutter\"><pre><div class=\"line\">1</div><div class=\"line\">2</div><div class=\"line\">3</div><div class=\"line\">4</div></pre></td><td class=\"code\"><pre><div class=\"line\">$ webpack --config XXX.js   //使用另一份配置文件（比如webpack.config2.js）来打包</div><div class=\"line\">$ webpack --watch   //监听变动并自动打包</div><div class=\"line\">$ webpack -p    //压缩混淆脚本，这个非常非常重要！</div><div class=\"line\">$ webpack -d    //生成map映射文件，告知哪些模块被最终打包到哪里了</div></pre></td></tr></table></figure>","next":{"title":"React 入门篇：什么是React","slug":"React-入门篇：什么是React","updated":1487580139617,"link":"","permalink":"http://www.fedjs.com/2017/02/React-入门篇：什么是React/","path":"2017/02/React-入门篇：什么是React/","photos":[],"comments":true,"source":"_posts/React-入门篇：什么是React.md","published":true},"categories":[],"tags":[]},{"title":"webpack入门篇：webpack-dev-server服务器","slug":"webpack入门篇：webpack-dev-server服务器","updated":1487318495621,"link":"","permalink":"http://www.fedjs.com/2017/02/webpack入门篇：webpack-dev-server服务器/","path":"2017/02/webpack入门篇：webpack-dev-server服务器/","photos":[],"comments":true,"source":"_posts/webpack入门篇：webpack-dev-server服务器.md","published":true,"excerpt":"","content":"","prev":{"title":"webpack插件篇：extract-text-webpack-plugin详解","slug":"webpack插件篇：extract-text-webpack-plugin详解","updated":1487557483632,"link":"","permalink":"http://www.fedjs.com/2017/02/webpack插件篇：extract-text-webpack-plugin详解/","path":"2017/02/webpack插件篇：extract-text-webpack-plugin详解/","photos":[],"comments":true,"source":"_posts/webpack插件篇：extract-text-webpack-plugin详解.md","published":true},"next":{"title":"webpack入门篇：多页面的资源分离引用（js/css按需引用）","slug":"webpack入门篇：多页面的资源分离引用（js-css按需引用）","updated":1487302839042,"link":"","permalink":"http://www.fedjs.com/2017/02/webpack入门篇：多页面的资源分离引用（js-css按需引用）/","path":"2017/02/webpack入门篇：多页面的资源分离引用（js-css按需引用）/","photos":[],"comments":true,"source":"_posts/webpack入门篇：多页面的资源分离引用（js-css按需引用）.md","published":true},"categories":[{"name":"webpack","slug":"webpack","path":"categories/webpack/","permalink":"http://www.fedjs.com/categories/webpack/","length":60}],"tags":[]},{"title":"关于借贷和裸条的一点思考","slug":"sale-yourself-for-money","updated":1487302839993,"link":"","permalink":"http://www.fedjs.com/2016/12/sale-yourself-for-money/","path":"2016/12/sale-yourself-for-money/","photos":[],"comments":true,"source":"_posts/sale-yourself-for-money.md","published":true,"excerpt":"","content":"<p>原文来自于我的“知乎问答” </p>\n<p><a href=\"https://www.zhihu.com/question/47736379/answer/134776288\" target=\"_blank\" rel=\"external\">如何从「裸条」看待这些借贷人的借贷观念？ - 蒋万万的回答 - 知乎</a></p>\n<p>关于借贷，我觉得祖辈的话还是很受用的。</p>\n<p><strong>1、你惦记别人的利，别人惦记着你的本，到最后，你本利无归，你觉得就这样结束了？别急，一般还有债！</strong><br><strong>2、背叛你的人永远都只会是你的朋友，或者看上去像是你朋友的人。</strong><br><strong>3、人心隔肚皮</strong><br><strong>4、铁打的营盘流水的兵</strong></p>\n<p>没有资本的人其实在现实世界上很难有选择的机会，总是很容易被各种诱惑所主宰，这次的网贷事件就可以说是无法避免的。<br><strong>（第一次生意）</strong><br>年轻的大学生（不分男女）总是有消费的欲望，我们暂不管他们去消费什么，这种需求是客观的存在的。我们呢，也不谈她们人性的光辉，善良或是邪恶、知足或是贪婪，只要有这种消费的动力，她们也只能别无选择的接收这种商品（贷款本身就是一种商品），惦记着这家或那家发布的“学生贷”的好处，交上人家要的正当信息资料，才能进入可以借贷的门槛，那么商家也要做这笔生意，权衡利弊以后觉得可以做你这笔生意，人家才可以把钱贷给你吧。双方觉得不错，签个合同画个押，生意就这样做好了。<br><strong>（第二次生意）</strong><br>商家这样的生意做多了，发现我们的客户（大学生没有钱没有具体的收入来源）质量也不是很好，拼死拼活也就赚这么多。不太好呀，怎么办？这样，你们不是还是需要花钱吗？那你可以多交点东西，比方说多提点利息和罚息，这样我们也更能赚的多些。大学生没办法，提就提吧，反正也是可以还完的，只要可以接收就签。双方觉得不错，签个合同画个押，生意就这样做好了。<br><strong>（第三次生意）</strong><br>“我为什么要签这家网贷，还有其他的可以选择，况且已经有一笔债了，先还完好了。”学生觉得后续情况不太乐观，不想签了。情绪一表现出来，商家就有察觉。“先还完也好，我这边有资金压力，嗯嗯，那你早点还好了。”商家也默认客户质量慢慢变得不好，总还是生意要做的，只不过不能给你那么多额度了，你也不再是我最想要的A类客户了。<br><strong>（第四次生意）</strong><br>逾期了 30天、60天、90天，看着利息每天都在长，自己的收入都填补不了这个坑。怎么办？那就不还了。商家不能等着呆账收不回钱啊。怎么办？等着数额慢慢的变大，再叫人去催收！学生一害怕就又只能老老实实的还钱了。学生想：反正商家也不知道我的钱是怎么来的，不如我再去其他的贷款网站借点钱，以后欠的可以慢慢还。然后又开始借款，拆了东墙补西墙，拆了西墙补东墙。合同签的越来越多，才发现商家的玩法都一样，自己的身上又多了不少的逾期账单。怎么办？<br><strong>（第五次生意）</strong></p>\n<p>商家A的喽啰，就是之前跟你当朋友的那个人，会主动给你提出一个解决方法来解决这种窘境。<br>“因为你借的少了所以你手里的钱的根本没有办法帮你解决实际的收入问题，你需要大幅度的提额，然后还掉我们的家的款，少了一家两家之后，你就会觉得轻松很多！要不逾期和罚息你这辈子都还不完！”商家A的喽啰说道。学生一听也确实是这个理，那就提提额吧。那具体怎么提呢？“要找口子的，你按照我要求的东西提供下，我帮你去找商家B！”喽啰说道。学生只能接收他提的条件。<br><strong>（第六次生意）</strong></p>\n<p>要什么都可以，只要能结束这种情况。<br>So…. ~你懂的！<br><strong>（第七次生意）</strong><br>没办法~忍气吞声<br><strong>（第八次生意）</strong></p>\n<p>没办法~如果不还清，同学们会怎么看我？！</p>\n<p><strong>（第九次生意）</strong></p>\n<p>没办法~信用快要破产了~</p>\n<p><strong>（第十次生意）</strong></p>\n<p>没办法~有人能好心救救我吗？ （现在人心应该没有那么好吧）</p>\n<p><strong>（第十一次生意）</strong></p>\n<p>~</p>\n<p>现在的生意好谈多了，做主子的感觉就是不一样！公司生意也变得的越来越好。商家不只做放贷还可以做其他的生意。</p>\n<p>几次生意过后，这种优势就会变得很明显！<br>但问题是 商业活动本身就是一种追逐胜利的游戏。<br>所以一方一定会想方设法的保持这种优势，这种金钱游戏的玩法最后都是 <strong>以营盘的胜利</strong> 而告终。</p>\n<p>你要明白，现在的女大学生都不傻，而是 <strong>被迫的趋利而为</strong> 而已<strong>！</strong></p>\n<p>小时候一直都生活在家教森严的爷爷奶奶家。<br>从小就接收着传统观念的影响，有很多话听起来好像登不上大雅之堂，但细细想想理确实还是那个理。<br>小声说句：放贷真的是这个世界上最完美的生意！<a href=\"javascript:;\" target=\"_blank\" rel=\"external\"><span>修改</span></a></p>","prev":{"title":"扫盲:JS模块化开发","slug":"talk-about-javascript-module-development","updated":1487224900988,"link":"","permalink":"http://www.fedjs.com/2016/12/talk-about-javascript-module-development/","path":"2016/12/talk-about-javascript-module-development/","photos":[],"comments":true,"source":"_posts/talk-about-javascript-module-development.md","published":true},"next":{"title":"嵊泗的离岛生活","slug":"Life-in-Shengsi-Islands","updated":1487224791195,"link":"","permalink":"http://www.fedjs.com/2016/12/Life-in-Shengsi-Islands/","path":"2016/12/Life-in-Shengsi-Islands/","photos":[],"comments":true,"source":"_posts/Life-in-Shengsi-Islands.md","published":true},"categories":[{"name":"思考随想","slug":"思考随想","path":"categories/思考随想/","permalink":"http://www.fedjs.com/categories/思考随想/","length":1}],"tags":[]},{"title":"webpack入门篇：config参数详解","slug":"webpack入门篇：config参数详解","updated":1487554456236,"link":"","permalink":"http://www.fedjs.com/2017/02/webpack入门篇：config参数详解/","path":"2017/02/webpack入门篇：config参数详解/","photos":[],"comments":true,"source":"_posts/webpack入门篇：config参数详解.md","published":true,"excerpt":"","content":"<h4 id=\"参数的详解配置（英文）\"><a href=\"#参数的详解配置（英文）\" class=\"headerlink\" title=\"参数的详解配置（英文）\"></a><a href=\"http://webpack.github.io/docs/configuration.html\" target=\"_blank\" rel=\"external\">参数的详解配置（英文）</a></h4><h1 id=\"plugins\"><a href=\"#plugins\" class=\"headerlink\" title=\"plugins\"></a>plugins</h1><p>插件项 </p>\n<figure class=\"highlight plain\"><table><tr><td class=\"gutter\"><pre><div class=\"line\">1</div></pre></td><td class=\"code\"><pre><div class=\"line\">plugins:[commonsPlugin]</div></pre></td></tr></table></figure>\n<h1 id=\"entry\"><a href=\"#entry\" class=\"headerlink\" title=\"entry\"></a>entry</h1><p>打包文件的入口点。</p>\n<h1 id=\"output\"><a href=\"#output\" class=\"headerlink\" title=\"output\"></a>output</h1><p>打包文件的输出点。</p>\n<h1 id=\"module-loader\"><a href=\"#module-loader\" class=\"headerlink\" title=\"module.loader\"></a>module.loader</h1><p>多个 loader 之间用“!”连接起来</p>\n<h1 id=\"resolve\"><a href=\"#resolve\" class=\"headerlink\" title=\"resolve\"></a>resolve</h1>","prev":{"title":"react-webpack 入门Demo展示","slug":"webpack-react-入门Demo展示","updated":1487234496375,"link":"","permalink":"http://www.fedjs.com/2017/02/webpack-react-入门Demo展示/","path":"2017/02/webpack-react-入门Demo展示/","photos":[],"comments":true,"source":"_posts/webpack-react-入门Demo展示.md","published":true},"next":{"title":"webpack插件篇：20个你必须知道的插件","slug":"webpack插件篇：20个你必须知道的插件","updated":1487318660246,"link":"","permalink":"http://www.fedjs.com/2017/02/webpack插件篇：20个你必须知道的插件/","path":"2017/02/webpack插件篇：20个你必须知道的插件/","photos":[],"comments":true,"source":"_posts/webpack插件篇：20个你必须知道的插件.md","published":true},"categories":[{"name":"webpack","slug":"webpack","path":"categories/webpack/","permalink":"http://www.fedjs.com/categories/webpack/","length":60}],"tags":[]},{"title":"webpack插件篇：AggressiveMergingPlugin详解","slug":"webpack插件篇：AggressiveMergingPlugin详解","updated":1487318852801,"link":"","permalink":"http://www.fedjs.com/2017/02/webpack插件篇：AggressiveMergingPlugin详解/","path":"2017/02/webpack插件篇：AggressiveMergingPlugin详解/","photos":[],"comments":true,"source":"_posts/webpack插件篇：AggressiveMergingPlugin详解.md","published":true,"excerpt":"","content":"<h1 id=\"用途说明\"><a href=\"#用途说明\" class=\"headerlink\" title=\"用途说明\"></a>用途说明</h1><p>AggressiveMergingPlugin ()</p>\n<h1 id=\"webpack-config-js配置\"><a href=\"#webpack-config-js配置\" class=\"headerlink\" title=\"webpack.config.js配置\"></a>webpack.config.js配置</h1><figure class=\"highlight js\"><table><tr><td class=\"gutter\"><pre><div class=\"line\">1</div><div class=\"line\">2</div></pre></td><td class=\"code\"><pre><div class=\"line\"></div><div class=\"line\"></div></pre></td></tr></table></figure>\n<h1 id=\"案例\"><a href=\"#案例\" class=\"headerlink\" title=\"案例\"></a>案例</h1><figure class=\"highlight js\"><table><tr><td class=\"gutter\"><pre><div class=\"line\">1</div><div class=\"line\">2</div></pre></td><td class=\"code\"><pre><div class=\"line\"></div><div class=\"line\"></div></pre></td></tr></table></figure>","prev":{"title":"webpack插件篇：DllPlugin详解","slug":"webpack插件篇：DllPlugin详解","updated":1487319023425,"link":"","permalink":"http://www.fedjs.com/2017/02/webpack插件篇：DllPlugin详解/","path":"2017/02/webpack插件篇：DllPlugin详解/","photos":[],"comments":true,"source":"_posts/webpack插件篇：DllPlugin详解.md","published":true},"next":{"title":"webpack插件篇：ngAnnotatePlugin详解","slug":"webpack插件篇：ngAnnotatePlugin详解","updated":1487561698043,"link":"","permalink":"http://www.fedjs.com/2017/02/webpack插件篇：ngAnnotatePlugin详解/","path":"2017/02/webpack插件篇：ngAnnotatePlugin详解/","photos":[],"comments":true,"source":"_posts/webpack插件篇：ngAnnotatePlugin详解.md","published":true},"categories":[{"name":"webpack","slug":"webpack","path":"categories/webpack/","permalink":"http://www.fedjs.com/categories/webpack/","length":60}],"tags":[]},{"title":"webpack插件篇：AppCachePlugin详解","slug":"webpack插件篇：AppCachePlugin详解","updated":1487318852849,"link":"","permalink":"http://www.fedjs.com/2017/02/webpack插件篇：AppCachePlugin详解/","path":"2017/02/webpack插件篇：AppCachePlugin详解/","photos":[],"comments":true,"source":"_posts/webpack插件篇：AppCachePlugin详解.md","published":true,"excerpt":"","content":"<h1 id=\"用途说明\"><a href=\"#用途说明\" class=\"headerlink\" title=\"用途说明\"></a>用途说明</h1><p>AppCachePlugin ()</p>\n<h1 id=\"webpack-config-js配置\"><a href=\"#webpack-config-js配置\" class=\"headerlink\" title=\"webpack.config.js配置\"></a>webpack.config.js配置</h1><figure class=\"highlight js\"><table><tr><td class=\"gutter\"><pre><div class=\"line\">1</div><div class=\"line\">2</div></pre></td><td class=\"code\"><pre><div class=\"line\"></div><div class=\"line\"></div></pre></td></tr></table></figure>\n<h1 id=\"案例\"><a href=\"#案例\" class=\"headerlink\" title=\"案例\"></a>案例</h1><figure class=\"highlight js\"><table><tr><td class=\"gutter\"><pre><div class=\"line\">1</div><div class=\"line\">2</div></pre></td><td class=\"code\"><pre><div class=\"line\"></div><div class=\"line\"></div></pre></td></tr></table></figure>","prev":{"title":"webpack插件篇：OfflinePlugin详解","slug":"webpack插件篇：OfflinePlugin详解","updated":1487320617328,"link":"","permalink":"http://www.fedjs.com/2017/02/webpack插件篇：OfflinePlugin详解/","path":"2017/02/webpack插件篇：OfflinePlugin详解/","photos":[],"comments":true,"source":"_posts/webpack插件篇：OfflinePlugin详解.md","published":true},"next":{"title":"webpack插件篇：DllReferencePlugin详解","slug":"webpack插件篇：DllReferencePlugin详解","updated":1487319023589,"link":"","permalink":"http://www.fedjs.com/2017/02/webpack插件篇：DllReferencePlugin详解/","path":"2017/02/webpack插件篇：DllReferencePlugin详解/","photos":[],"comments":true,"source":"_posts/webpack插件篇：DllReferencePlugin详解.md","published":true},"categories":[{"name":"webpack","slug":"webpack","path":"categories/webpack/","permalink":"http://www.fedjs.com/categories/webpack/","length":60}],"tags":[]},{"title":"webpack插件篇：AngularPlugin详解","slug":"webpack插件篇：AngularPlugin详解","updated":1487554559913,"link":"","permalink":"http://www.fedjs.com/2017/02/webpack插件篇：AngularPlugin详解/","path":"2017/02/webpack插件篇：AngularPlugin详解/","photos":[],"comments":true,"source":"_posts/webpack插件篇：AngularPlugin详解.md","published":true,"excerpt":"","content":"<h1 id=\"用途说明\"><a href=\"#用途说明\" class=\"headerlink\" title=\"用途说明\"></a>用途说明</h1><p>AngularPlugin ()</p>\n<p>Use angular.js modules with webpack.</p>\n<h1 id=\"webpack-config-js配置\"><a href=\"#webpack-config-js配置\" class=\"headerlink\" title=\"webpack.config.js配置\"></a>webpack.config.js配置</h1><figure class=\"highlight js\"><table><tr><td class=\"gutter\"><pre><div class=\"line\">1</div><div class=\"line\">2</div></pre></td><td class=\"code\"><pre><div class=\"line\"></div><div class=\"line\"></div></pre></td></tr></table></figure>\n<h1 id=\"案例\"><a href=\"#案例\" class=\"headerlink\" title=\"案例\"></a>案例</h1><figure class=\"highlight js\"><table><tr><td class=\"gutter\"><pre><div class=\"line\">1</div><div class=\"line\">2</div></pre></td><td class=\"code\"><pre><div class=\"line\"></div><div class=\"line\"></div></pre></td></tr></table></figure>","prev":{"title":"webpack插件篇：DefinePlugin详解","slug":"webpack插件篇：DefinePlugin详解","updated":1487561711382,"link":"","permalink":"http://www.fedjs.com/2017/02/webpack插件篇：DefinePlugin详解/","path":"2017/02/webpack插件篇：DefinePlugin详解/","photos":[],"comments":true,"source":"_posts/webpack插件篇：DefinePlugin详解.md","published":true},"next":{"title":"webpack插件篇：LabeledModulesPlugin详解","slug":"webpack插件篇：LabeledModulesPlugin详解","updated":1487320343572,"link":"","permalink":"http://www.fedjs.com/2017/02/webpack插件篇：LabeledModulesPlugin详解/","path":"2017/02/webpack插件篇：LabeledModulesPlugin详解/","photos":[],"comments":true,"source":"_posts/webpack插件篇：LabeledModulesPlugin详解.md","published":true},"categories":[{"name":"webpack","slug":"webpack","path":"categories/webpack/","permalink":"http://www.fedjs.com/categories/webpack/","length":60}],"tags":[]},{"title":"webpack插件篇：BannerPlugin详解","slug":"webpack插件篇：BannerPlugin详解","updated":1487554681940,"link":"","permalink":"http://www.fedjs.com/2017/02/webpack插件篇：BannerPlugin详解/","path":"2017/02/webpack插件篇：BannerPlugin详解/","photos":[],"comments":true,"source":"_posts/webpack插件篇：BannerPlugin详解.md","published":true,"excerpt":"","content":"<h1 id=\"用途说明\"><a href=\"#用途说明\" class=\"headerlink\" title=\"用途说明\"></a>用途说明</h1><p>BannerPlugin ()</p>\n<p>Adds a banner to the top of each generated chunk.</p>\n<ul>\n<li><p><code>banner</code> a string, it will be wrapped in a comment</p>\n</li>\n<li><p><code>options.raw</code> if true, banner will not be wrapped in a comment</p>\n</li>\n<li><p><code>options.entryOnly</code> if true, the banner will only be added to the entry chunks.</p>\n</li>\n</ul>\n<h1 id=\"webpack-config-js配置\"><a href=\"#webpack-config-js配置\" class=\"headerlink\" title=\"webpack.config.js配置\"></a>webpack.config.js配置</h1><figure class=\"highlight js\"><table><tr><td class=\"gutter\"><pre><div class=\"line\">1</div></pre></td><td class=\"code\"><pre><div class=\"line\"><span class=\"keyword\">new</span> webpack.BannerPlugin(banner, options)</div></pre></td></tr></table></figure>\n<h1 id=\"案例\"><a href=\"#案例\" class=\"headerlink\" title=\"案例\"></a>案例</h1><figure class=\"highlight js\"><table><tr><td class=\"gutter\"><pre><div class=\"line\">1</div><div class=\"line\">2</div></pre></td><td class=\"code\"><pre><div class=\"line\"></div><div class=\"line\"></div></pre></td></tr></table></figure>","prev":{"title":"webpack插件篇：DedupePlugin详解","slug":"webpack插件篇：DedupePlugin详解","updated":1487319022599,"link":"","permalink":"http://www.fedjs.com/2017/02/webpack插件篇：DedupePlugin详解/","path":"2017/02/webpack插件篇：DedupePlugin详解/","photos":[],"comments":true,"source":"_posts/webpack插件篇：DedupePlugin详解.md","published":true},"next":{"title":"webpack插件篇：EnvironmentPlugin详解","slug":"webpack插件篇：EnvironmentPlugin详解","updated":1487319023252,"link":"","permalink":"http://www.fedjs.com/2017/02/webpack插件篇：EnvironmentPlugin详解/","path":"2017/02/webpack插件篇：EnvironmentPlugin详解/","photos":[],"comments":true,"source":"_posts/webpack插件篇：EnvironmentPlugin详解.md","published":true},"categories":[{"name":"webpack","slug":"webpack","path":"categories/webpack/","permalink":"http://www.fedjs.com/categories/webpack/","length":60}],"tags":[]},{"title":"webpack插件篇：Config配置类插件有哪些？","slug":"webpack插件篇：Config配置类插件有哪些","updated":1487320343415,"link":"","permalink":"http://www.fedjs.com/2017/02/webpack插件篇：Config配置类插件有哪些/","path":"2017/02/webpack插件篇：Config配置类插件有哪些/","photos":[],"comments":true,"source":"_posts/webpack插件篇：Config配置类插件有哪些.md","published":true,"excerpt":"","content":"","prev":{"title":"webpack插件篇：Output输出类插件有哪些？","slug":"webpack插件篇：Output输出类插件有哪些","updated":1487319023102,"link":"","permalink":"http://www.fedjs.com/2017/02/webpack插件篇：Output输出类插件有哪些/","path":"2017/02/webpack插件篇：Output输出类插件有哪些/","photos":[],"comments":true,"source":"_posts/webpack插件篇：Output输出类插件有哪些.md","published":true},"next":{"title":"webpack插件篇：CommonsChunkPlugin详解","slug":"webpack插件篇：CommonsChunkPlugin详解","updated":1487555806661,"link":"","permalink":"http://www.fedjs.com/2017/02/webpack插件篇：CommonsChunkPlugin详解/","path":"2017/02/webpack插件篇：CommonsChunkPlugin详解/","photos":[],"comments":true,"source":"_posts/webpack插件篇：CommonsChunkPlugin详解.md","published":true},"categories":[{"name":"webpack","slug":"webpack","path":"categories/webpack/","permalink":"http://www.fedjs.com/categories/webpack/","length":60}],"tags":[]},{"title":"webpack插件篇：20个你必须知道的插件","slug":"webpack插件篇：20个你必须知道的插件","updated":1487318660246,"link":"","permalink":"http://www.fedjs.com/2017/02/webpack插件篇：20个你必须知道的插件/","path":"2017/02/webpack插件篇：20个你必须知道的插件/","photos":[],"comments":true,"source":"_posts/webpack插件篇：20个你必须知道的插件.md","published":true,"excerpt":"","content":"<h1 id=\"webpack插件党推荐\"><a href=\"#webpack插件党推荐\" class=\"headerlink\" title=\"webpack插件党推荐\"></a>webpack插件党推荐</h1>","prev":{"title":"webpack入门篇：config参数详解","slug":"webpack入门篇：config参数详解","updated":1487554456236,"link":"","permalink":"http://www.fedjs.com/2017/02/webpack入门篇：config参数详解/","path":"2017/02/webpack入门篇：config参数详解/","photos":[],"comments":true,"source":"_posts/webpack入门篇：config参数详解.md","published":true},"next":{"title":"npm使用入门","slug":"npm使用入门","updated":1487225121961,"link":"","permalink":"http://www.fedjs.com/2017/02/npm使用入门/","path":"2017/02/npm使用入门/","photos":[],"comments":true,"source":"_posts/npm使用入门.md","published":true},"categories":[{"name":"webpack","slug":"webpack","path":"categories/webpack/","permalink":"http://www.fedjs.com/categories/webpack/","length":60}],"tags":[]}],"total":8}