{"base":"archives/","current":5,"prev":4,"next":6,"current_url":"archives//5","prev_link":"archives//4","next_link":"archives//6","posts":[{"title":"webpack插件篇：Module Styles模块类型插件有哪些？","slug":"webpack插件篇：Module-Styles模块类型插件有哪些","updated":1487320343540,"link":"","permalink":"http://www.fedjs.com/2017/02/webpack插件篇：Module-Styles模块类型插件有哪些/","path":"2017/02/webpack插件篇：Module-Styles模块类型插件有哪些/","photos":[],"comments":true,"source":"_posts/webpack插件篇：Module-Styles模块类型插件有哪些.md","published":true},{"title":"webpack插件篇：NgRequirePlugin详解","slug":"webpack插件篇：NgRequirePlugin详解","updated":1487319023755,"link":"","permalink":"http://www.fedjs.com/2017/02/webpack插件篇：NgRequirePlugin详解/","path":"2017/02/webpack插件篇：NgRequirePlugin详解/","photos":[],"comments":true,"source":"_posts/webpack插件篇：NgRequirePlugin详解.md","published":true},{"title":"webpack插件篇：NoErrorsPlugin详解","slug":"webpack插件篇：NoErrorsPlugin详解","updated":1487320207551,"link":"","permalink":"http://www.fedjs.com/2017/02/webpack插件篇：NoErrorsPlugin详解/","path":"2017/02/webpack插件篇：NoErrorsPlugin详解/","photos":[],"comments":true,"source":"_posts/webpack插件篇：NoErrorsPlugin详解.md","published":true},{"title":"webpack插件篇：NormalModuleReplacementPlugin详解","slug":"webpack插件篇：NormalModuleReplacementPlugin详解","updated":1487309202493,"link":"","permalink":"http://www.fedjs.com/2017/02/webpack插件篇：NormalModuleReplacementPlugin详解/","path":"2017/02/webpack插件篇：NormalModuleReplacementPlugin详解/","photos":[],"comments":true,"source":"_posts/webpack插件篇：NormalModuleReplacementPlugin详解.md","published":true},{"title":"webpack插件篇：OccurrenceOrderPlugin详解","slug":"webpack插件篇：OccurrenceOrderPlugin详解","updated":1487320555228,"link":"","permalink":"http://www.fedjs.com/2017/02/webpack插件篇：OccurrenceOrderPlugin详解/","path":"2017/02/webpack插件篇：OccurrenceOrderPlugin详解/","photos":[],"comments":true,"source":"_posts/webpack插件篇：OccurrenceOrderPlugin详解.md","published":true},{"title":"webpack插件篇：MinChunkSizePlugin详解","slug":"webpack插件篇：MinChunkSizePlugin详解","updated":1487320495563,"link":"","permalink":"http://www.fedjs.com/2017/02/webpack插件篇：MinChunkSizePlugin详解/","path":"2017/02/webpack插件篇：MinChunkSizePlugin详解/","photos":[],"comments":true,"source":"_posts/webpack插件篇：MinChunkSizePlugin详解.md","published":true},{"title":"webpack插件篇：OfflinePlugin详解","slug":"webpack插件篇：OfflinePlugin详解","updated":1487320617328,"link":"","permalink":"http://www.fedjs.com/2017/02/webpack插件篇：OfflinePlugin详解/","path":"2017/02/webpack插件篇：OfflinePlugin详解/","photos":[],"comments":true,"source":"_posts/webpack插件篇：OfflinePlugin详解.md","published":true},{"title":"webpack插件篇：Optimize优化类插件有哪些？","slug":"webpack插件篇：Optimize优化类插件有哪些","updated":1487320343630,"link":"","permalink":"http://www.fedjs.com/2017/02/webpack插件篇：Optimize优化类插件有哪些/","path":"2017/02/webpack插件篇：Optimize优化类插件有哪些/","photos":[],"comments":true,"source":"_posts/webpack插件篇：Optimize优化类插件有哪些.md","published":true},{"title":"webpack插件篇：Output输出类插件有哪些？","slug":"webpack插件篇：Output输出类插件有哪些","updated":1487319023102,"link":"","permalink":"http://www.fedjs.com/2017/02/webpack插件篇：Output输出类插件有哪些/","path":"2017/02/webpack插件篇：Output输出类插件有哪些/","photos":[],"comments":true,"source":"_posts/webpack插件篇：Output输出类插件有哪些.md","published":true},{"title":"webpack插件篇：PrefetchPlugin详解","slug":"webpack插件篇：PrefetchPlugin详解","updated":1487310370874,"link":"","permalink":"http://www.fedjs.com/2017/02/webpack插件篇：PrefetchPlugin详解/","path":"2017/02/webpack插件篇：PrefetchPlugin详解/","photos":[],"comments":true,"source":"_posts/webpack插件篇：PrefetchPlugin详解.md","published":true}],"total":7}