{"title":"webpack插件篇：WebpackPluginGraphqlSchemaHot详解","slug":"webpack插件篇：WebpackPluginGraphqlSchemaHot详解","updated":1487319066595,"link":"","permalink":"http://www.fedjs.com/2017/02/webpack插件篇：WebpackPluginGraphqlSchemaHot详解/","path":"2017/02/webpack插件篇：WebpackPluginGraphqlSchemaHot详解/","photos":[],"comments":true,"source":"_posts/webpack插件篇：WebpackPluginGraphqlSchemaHot详解.md","published":true,"excerpt":"","content":"<h1 id=\"用途说明\"><a href=\"#用途说明\" class=\"headerlink\" title=\"用途说明\"></a>用途说明</h1><p>WebpackPluginGraphqlSchemaHot ()</p>\n<p>This plugin tracks changes in your GraphQL Schema and generates its introspection in json and txt formats.</p>\n<h1 id=\"webpack-config-js配置\"><a href=\"#webpack-config-js配置\" class=\"headerlink\" title=\"webpack.config.js配置\"></a>webpack.config.js配置</h1><figure class=\"highlight js\"><table><tr><td class=\"gutter\"><pre><div class=\"line\">1</div><div class=\"line\">2</div><div class=\"line\">3</div><div class=\"line\">4</div><div class=\"line\">5</div><div class=\"line\">6</div><div class=\"line\">7</div><div class=\"line\">8</div><div class=\"line\">9</div><div class=\"line\">10</div><div class=\"line\">11</div><div class=\"line\">12</div><div class=\"line\">13</div><div class=\"line\">14</div><div class=\"line\">15</div><div class=\"line\">16</div><div class=\"line\">17</div><div class=\"line\">18</div></pre></td><td class=\"code\"><pre><div class=\"line\"><span class=\"keyword\">const</span> path = <span class=\"built_in\">require</span>(<span class=\"string\">'path'</span>);</div><div class=\"line\"><span class=\"keyword\">const</span> WebpackPluginGraphqlSchemaHot = <span class=\"built_in\">require</span>(<span class=\"string\">'webpack-plugin-graphql-schema-hot'</span>);</div><div class=\"line\"></div><div class=\"line\"><span class=\"keyword\">var</span> plugins = [];</div><div class=\"line\">&#123;</div><div class=\"line\">  <span class=\"attr\">plugins</span>: [</div><div class=\"line\">    <span class=\"keyword\">new</span> WebpackPluginGraphqlSchemaHot(&#123;</div><div class=\"line\">      <span class=\"attr\">schemaPath</span>: path.resolve(__dirname, <span class=\"string\">'../schema/index.js'</span>),</div><div class=\"line\">      <span class=\"attr\">output</span>: &#123;</div><div class=\"line\">        <span class=\"attr\">json</span>: path.resolve(__dirname, <span class=\"string\">'../build/schema.graphql.json'</span>),</div><div class=\"line\">        <span class=\"attr\">txt</span>: path.resolve(__dirname, <span class=\"string\">'../build/schema.graphql.txt'</span>),</div><div class=\"line\">      &#125;,</div><div class=\"line\">      <span class=\"attr\">runOnStart</span>: <span class=\"literal\">true</span>,</div><div class=\"line\">      <span class=\"attr\">verbose</span>: <span class=\"literal\">true</span>,</div><div class=\"line\">      <span class=\"attr\">hideErrors</span>: <span class=\"literal\">false</span>,</div><div class=\"line\">    &#125;),</div><div class=\"line\">  ]</div><div class=\"line\">&#125;</div></pre></td></tr></table></figure>\n<h1 id=\"案例\"><a href=\"#案例\" class=\"headerlink\" title=\"案例\"></a>案例</h1><figure class=\"highlight js\"><table><tr><td class=\"gutter\"><pre><div class=\"line\">1</div><div class=\"line\">2</div></pre></td><td class=\"code\"><pre><div class=\"line\"></div><div class=\"line\"></div></pre></td></tr></table></figure>","prev":{"title":"webpack入门篇：多页面的资源分离引用（js/css按需引用）","slug":"webpack入门篇：多页面的资源分离引用（js-css按需引用）","updated":1487302839042,"link":"","permalink":"http://www.fedjs.com/2017/02/webpack入门篇：多页面的资源分离引用（js-css按需引用）/","path":"2017/02/webpack入门篇：多页面的资源分离引用（js-css按需引用）/","photos":[],"comments":true,"source":"_posts/webpack入门篇：多页面的资源分离引用（js-css按需引用）.md","published":true},"next":{"title":"webpack插件篇：FaviconsWebpackPlugin详解","slug":"webpack插件篇：FaviconsWebpackPlugin详解","updated":1487319121852,"link":"","permalink":"http://www.fedjs.com/2017/02/webpack插件篇：FaviconsWebpackPlugin详解/","path":"2017/02/webpack插件篇：FaviconsWebpackPlugin详解/","photos":[],"comments":true,"source":"_posts/webpack插件篇：FaviconsWebpackPlugin详解.md","published":true},"categories":[{"name":"webpack","slug":"webpack","path":"categories/webpack/","permalink":"http://www.fedjs.com/categories/webpack/","length":59}],"tags":[]}